basilsweepercrawler/__init__.py
basilsweepercrawler/crunchbase_scraper.py
basilsweepercrawler/github_scraper.py
basilsweepercrawler/linkedin_gym.py
basilsweepercrawler/linkedin_scraper.py
basilsweepercrawler/stackexchange_scraper.py
basilsweepercrawler/web_sweepers.py
basilsweepercrawler/format_data/apicall.py
basilsweepercrawler/format_data/exceptions.py
basilsweepercrawler/format_data/format_candidate.py
basilsweepercrawler/format_data/format_linkedin.py
basilsweepercrawler/format_data/test_utils.py
basilsweepercrawler-0.0.12.dist-info/METADATA
basilsweepercrawler-0.0.12.dist-info/WHEEL
basilsweepercrawler-0.0.12.dist-info/top_level.txt
basilsweepercrawler-0.0.12.dist-info/RECORD
